Flask_Coralillo-0.1.3.dist-info/DESCRIPTION.rst
Flask_Coralillo-0.1.3.dist-info/METADATA
Flask_Coralillo-0.1.3.dist-info/RECORD
Flask_Coralillo-0.1.3.dist-info/WHEEL
Flask_Coralillo-0.1.3.dist-info/metadata.json
Flask_Coralillo-0.1.3.dist-info/top_level.txt
flask_coralillo/__init__.py
