Metadata-Version: 2.0
Name: Flask-Coralillo
Version: 0.1.3
Summary: Flask module for the Coralillo redis ORM
Home-page: https://github.com/getfleety/flask-coralillo
Author: Abraham Toriz Cruz
Author-email: categulario@gmail.com
License: MIT
Platform: any
Classifier: Environment :: Web Environment
Classifier: Intended Audience :: Developers
Classifier: License :: OSI Approved :: MIT License
Classifier: Operating System :: OS Independent
Classifier: Programming Language :: Python
Classifier: Topic :: Internet :: WWW/HTTP :: Dynamic Content
Classifier: Topic :: Software Development :: Libraries :: Python Modules
Requires-Dist: Flask
Requires-Dist: coralillo
